srt_fracture_control/__init__.py
srt_fracture_control/pressure_deviation_detector.py
srt_fracture_control/rate_controller.py
srt_fracture_control/reservoir_simulator.py
srt_fracture_control-0.1.1.dist-info/METADATA
srt_fracture_control-0.1.1.dist-info/WHEEL
srt_fracture_control-0.1.1.dist-info/licenses/LICENSE
srt_fracture_control-0.1.1.dist-info/RECORD
