Metadata-Version: 2.4
Name: srt-fracture-control
Version: 0.1.1
Summary: A Python library for automated monitoring and control of induced fracturing and fracture opening in injection wells using step rate tests and pressure transient analysis.
Project-URL: Homepage, https://github.com/adrianambrus/srt-fracture-control
Project-URL: Repository, https://github.com/adrianambrus/srt-fracture-control.git
Project-URL: Issues, https://github.com/adrianambrus/srt-fracture-control/issues
Author: A. Ambrus, U.J.F. Aarsnes
License: MIT License
License-File: LICENSE
Keywords: automated-rate-control,bourdet-derivative,fracture-opening-pressure,pressure-transient-analysis,safe-operating-envelope,step-rate-test
Classifier: Development Status :: 4 - Beta
Classifier: Intended Audience :: Science/Research
Classifier: License :: OSI Approved :: MIT License
Classifier: Programming Language :: Python :: 3.8
Classifier: Programming Language :: Python :: 3.9
Classifier: Programming Language :: Python :: 3.10
Classifier: Topic :: Scientific/Engineering
Requires-Python: >=3.8
Requires-Dist: numpy>=1.21
Requires-Dist: openpyxl>=3.1.5
Requires-Dist: pandas>=1.3.0
Requires-Dist: scipy>=1.10
